<?xml version="1.0" encoding="UTF-8"?>
<con:resource name="{id}" path="/api/studentsDetails/{id}" id="5f00916c-84af-41a4-8606-201a6d6eea8d" xmlns:con="http://eviware.com/soapui/config"><con:settings><con:setting id="5f00916c-84af-41a4-8606-201a6d6eea8dfileName">%7Bid%7D</con:setting></con:settings><con:parameters><con:parameter required="true"><con:name>id</con:name><con:value>id</con:value><con:style>TEMPLATE</con:style><con:default>id</con:default></con:parameter></con:parameters><con:method name="Method 1" id="e8c81a71-7805-4d6f-abcc-610e92598e17" method="DELETE"><con:settings/><con:parameters/><con:request name="Request 1" id="fa1f218e-a89f-4e6d-80a2-68c18216b4c0" mediaType="application/json" postQueryString="false"><con:settings><con:setting id="com.eviware.soapui.impl.wsdl.WsdlRequest@request-headers">&lt;xml-fragment/></con:setting></con:settings><con:endpoint>https://thetestingworldapi.com</con:endpoint><con:request/><con:originalUri>https://thetestingworldapi.com/api/studentsDetails/7387863</con:originalUri><con:credentials><con:authType>No Authorization</con:authType></con:credentials><con:jmsConfig JMSDeliveryMode="PERSISTENT"/><con:parameters><con:entry key="id" value="7387863"/></con:parameters><con:parameterOrder><con:entry>id</con:entry></con:parameterOrder></con:request></con:method></con:resource>